<?xml version="1.0" encoding="UTF-8"?>
<objects serializationModel="Studio.02.02.00">
	<object class="AudioFile" id="{817f7a99-efba-4e51-ad7d-fea3cab78387}">
		<property name="assetPath">
			<value>sfx2.wav</value>
		</property>
		<property name="frequencyInKHz">
			<value>44.0999985</value>
		</property>
		<property name="channelCount">
			<value>2</value>
		</property>
		<property name="length">
			<value>2.3616099773242629</value>
		</property>
		<relationship name="masterAssetFolder">
			<destination>{9822f2fb-4816-49a1-b9f0-7d767106efce}</destination>
		</relationship>
	</object>
</objects>
